[
    {
        "title": "Languages",
        "tech": [
            "Python",
            "SQL",
            "JavaScript",
            "HTML",
            "CSS",
            "D3.js"
        ]
    },
    {
        "title": "Web Development",
        "tech": [
            "Django",
            "Django Rest Framework",
            "Celery",
            "GraphQL (Ariadne)",
            "JavaScript (DOM manipulation, AJAX)",
            "Unit Testing with Django (Pytest)",
            "JWT",
            "Gunicorn",
            "Nginx"
        ]
    },
    {
        "title": "Big Data & Cloud",
        "tech": [
            "Amazon Web Services",
            "Microsoft Azure",
            "PySpark",
            "Apache Kafka",
            "Hadoop",
            "Airflow",
            "Hive"
        ]
    },
    {
        "title": "Databases",
        "tech": [
            "PostgerSQL",
            "MySQL",
            "DynamoDB",
            "MongoDB",
            "Neo4J",
            "Redis"
        ]
    },
    {
        "title": "AI & ML",
        "tech": [
            "XGBoost",
            "OpenCV",
            "Pandas",
            "Numpy",
            "Scikit-learn",
            "Matplotlib",
            "Seaborn"
        ]
    },
    {
        "title": "Computer Vision",
        "tech": [
            "TensorFlow",
            "Keras",
            "PyTorch",
            "YOLO",
            "Ultralytics",
            "Supervision",
            "Roboflow"
        ]
    },
    {
        "title": "DevOps & Tools",
        "tech": [
            "Git",
            "GitHub Workflow",
            "GitLab - CI/CD",
            "Docker",
            "PEP 8 (Python Code Style)",
            "Postman"
        ]
    }
]